async_buzzer.py
circuitpython_async_buzzer-1.0.1.dist-info/LICENSE
circuitpython_async_buzzer-1.0.1.dist-info/METADATA
circuitpython_async_buzzer-1.0.1.dist-info/WHEEL
circuitpython_async_buzzer-1.0.1.dist-info/top_level.txt
circuitpython_async_buzzer-1.0.1.dist-info/RECORD
