Metadata-Version: 2.1
Name: circuitpython-async-buzzer
Version: 1.0.1
Summary: Play simple tunes on a piezo buzzer asynchronously
Author-email: Adafruit Industries <circuitpython@adafruit.com>
License: MIT
Project-URL: Homepage, https://github.com/furbrain/CircuitPython_async_buzzer
Keywords: adafruit,blinka,circuitpython,micropython,async_buzzer,asyncio,buzzer,piezo,music,tune,alert,async,asynchronous
Classifier: Intended Audience :: Developers
Classifier: Topic :: Software Development :: Libraries
Classifier: Topic :: Software Development :: Embedded Systems
Classifier: Topic :: System :: Hardware
Classifier: License :: OSI Approved :: MIT License
Classifier: Programming Language :: Python :: 3
License-File: LICENSE
Requires-Dist: Adafruit-Blinka
Requires-Dist: adafruit-circuitpython-asyncio
Provides-Extra: optional
